cleartest.py
runtests
setup.py
cleartest.egg-info/PKG-INFO
cleartest.egg-info/SOURCES.txt
cleartest.egg-info/dependency_links.txt
cleartest.egg-info/requires.txt
cleartest.egg-info/top_level.txt