Metadata-Version: 1.0
Name: cleartest
Version: 0.911
Summary: Lightweight testing framework for Python 2.7 and Python 3
Home-page: https://github.com/sbarba/cleartest
Author: Steve Barba
Author-email: UNKNOWN
License: MIT
Platform: UNKNOWN
